multimethod/__init__.py
multimethod/multimethod.py
todofcpy/__init__.py
todofcpy/visualization/__init__.py
todofcpy/visualization/animation.py
todofcpy/visualization/error.py
todofcpy/visualization/graph.py
todofcpy-0.3.1.dist-info/LICENSE
todofcpy-0.3.1.dist-info/METADATA
todofcpy-0.3.1.dist-info/WHEEL
todofcpy-0.3.1.dist-info/top_level.txt
todofcpy-0.3.1.dist-info/RECORD
